moonshine_cpp-0.1.4.data/purelib/moonshine_cpp/LICENSE
moonshine_cpp-0.1.4.data/purelib/moonshine_cpp/__init__.py
moonshine_cpp-0.1.4.data/purelib/moonshine_cpp/libmoonshine.dylib
moonshine_cpp-0.1.4.data/purelib/moonshine_cpp/libonnxruntime.1.22.1.dylib
moonshine_cpp-0.1.4.data/purelib/moonshine_cpp/moonshine_cpp.py
moonshine_cpp-0.1.4.data/purelib/moonshine_cpp/test.py
moonshine_cpp-0.1.4.data/purelib/moonshine_cpp/models/base-en/decoder_model_merged.ort
moonshine_cpp-0.1.4.data/purelib/moonshine_cpp/models/base-en/encoder_model.ort
moonshine_cpp-0.1.4.data/purelib/moonshine_cpp/models/base-en/tokenizer.bin
moonshine_cpp-0.1.4.data/purelib/moonshine_cpp/test-data/beckett.wav
moonshine_cpp-0.1.4.dist-info/METADATA
moonshine_cpp-0.1.4.dist-info/WHEEL
moonshine_cpp-0.1.4.dist-info/top_level.txt
moonshine_cpp-0.1.4.dist-info/RECORD
