Metadata-Version: 2.4
Name: moonshine_cpp
Version: 0.1.4
Summary: Moonshine lightweight transcription library
Author-email: Moonshine AI <contact@moonshine.ai>
Maintainer-email: Moonshine AI <contact@moonshine.ai>
License: MIT
Project-URL: Homepage, https://github.com/moonshine-ai/moonshine.cpp
Project-URL: Repository, https://github.com/moonshine-ai/moonshine.cpp
Project-URL: Issues, https://github.com/moonshine-ai/moonshine.cpp/issues
Keywords: transcription,speech,ai,onnx,cpp
Classifier: Development Status :: 4 - Beta
Classifier: Intended Audience :: Developers
Classifier: License :: OSI Approved :: MIT License
Classifier: Operating System :: OS Independent
Classifier: Programming Language :: Python :: 3
Classifier: Programming Language :: Python :: 3.7
Classifier: Programming Language :: Python :: 3.8
Classifier: Programming Language :: Python :: 3.9
Classifier: Programming Language :: Python :: 3.10
Classifier: Programming Language :: Python :: 3.11
Classifier: Programming Language :: Python :: 3.12
Classifier: Topic :: Scientific/Engineering :: Artificial Intelligence
Classifier: Topic :: Multimedia :: Sound/Audio :: Speech
Requires-Python: >=3.7
